pythonwhat_ext.py
setup.cfg
setup.py
pythonwhat_ext.egg-info/PKG-INFO
pythonwhat_ext.egg-info/SOURCES.txt
pythonwhat_ext.egg-info/dependency_links.txt
pythonwhat_ext.egg-info/requires.txt
pythonwhat_ext.egg-info/top_level.txt