Metadata-Version: 1.0
Name: pythonwhat-ext
Version: 0.0.1
Summary: pythonwhat extensions - high level SCTs
Home-page: https://github.com/datacamp/pythonwhat-ext
Author: Michael Chow
Author-email: michael@datacamp.com
License: UNKNOWN
Platform: UNKNOWN
